PFP_Model-1.0.2.dev1.dist-info/DESCRIPTION.rst
PFP_Model-1.0.2.dev1.dist-info/METADATA
PFP_Model-1.0.2.dev1.dist-info/RECORD
PFP_Model-1.0.2.dev1.dist-info/WHEEL
PFP_Model-1.0.2.dev1.dist-info/metadata.json
PFP_Model-1.0.2.dev1.dist-info/top_level.txt
pfpmodel/__init__.py
pfpmodel/pfp_graph.py
