Metadata-Version: 2.0
Name: PFP-Model
Version: 1.0.2.dev1
Summary: generate a PFP Model to reproduces the Internet
Home-page: https://github.com/HaoruoLiu/
Author: Haoruo Liu
Author-email: haoruo.liu@qq.com
License: UNKNOWN
Platform: UNKNOWN
